<annotation>
	<folder>images</folder>
	<filename>b9ea0c01-c98d-11f0-92c7-005056c00008.jpg</filename>
	<path>C:\Users\souza\projects\chris-ai-game-object-detection\data\images\b9ea0c01-c98d-11f0-92c7-005056c00008.jpg</path>
	<source>
		<database>Unknown</database>
	</source>
	<size>
		<width>640</width>
		<height>481</height>
		<depth>3</depth>
	</size>
	<segmented>0</segmented>
	<object>
		<name>right_obs</name>
		<pose>Unspecified</pose>
		<truncated>0</truncated>
		<difficult>0</difficult>
		<bndbox>
			<xmin>358</xmin>
			<ymin>127</ymin>
			<xmax>462</xmax>
			<ymax>186</ymax>
		</bndbox>
	</object>
	<object>
		<name>timberman</name>
		<pose>Unspecified</pose>
		<truncated>0</truncated>
		<difficult>0</difficult>
		<bndbox>
			<xmin>179</xmin>
			<ymin>290</ymin>
			<xmax>267</xmax>
			<ymax>401</ymax>
		</bndbox>
	</object>
</annotation>
